fridaylabs/__init__.py
fridaylabs/client.py
fridaylabs/endpoints/__init__.py
fridaylabs/endpoints/chat.py
fridaylabs/endpoints/other_endpoint.py
fridaylabs/utils/__init__.py
fridaylabs/utils/colors.py
tests/__init__.py
tests/test_chat.py
tests/test_client.py
fridaylabs-0.2.4.dist-info/LICENSE
fridaylabs-0.2.4.dist-info/METADATA
fridaylabs-0.2.4.dist-info/WHEEL
fridaylabs-0.2.4.dist-info/top_level.txt
fridaylabs-0.2.4.dist-info/RECORD
