Metadata-Version: 2.1
Name: fridaylabs
Version: 0.2.4
Summary: A Python client library to interact with the FridayLabs AI API
Home-page: https://github.com/ImJustRicky/fridaylabs-package
Author: FridayLabs
Author-email: fridaylabs@fridaylabs.ai
Project-URL: Documentation, https://github.com/ImJustRicky/fridaylabs-package#readme
Project-URL: Source, https://github.com/ImJustRicky/fridaylabs-package
Keywords: fridaylabs ai api client
Classifier: Development Status :: 4 - Beta
Classifier: Intended Audience :: Developers
Classifier: Topic :: Software Development :: Libraries :: Python Modules
Classifier: Programming Language :: Python :: 3
Classifier: Programming Language :: Python :: 3.7
Classifier: Programming Language :: Python :: 3.8
Classifier: Programming Language :: Python :: 3.9
Classifier: License :: OSI Approved :: MIT License
Classifier: Operating System :: OS Independent
Requires-Python: >=3.7
License-File: LICENSE
Requires-Dist: requests >=2.25.1
